harlequelrah_fastapi/__init__.py
harlequelrah_fastapi/__main__.py
harlequelrah_fastapi/authentication/__init__.py
harlequelrah_fastapi/authentication/authenticate.py
harlequelrah_fastapi/authentication/token.py
harlequelrah_fastapi/authorization/__init__.py
harlequelrah_fastapi/authorization/meta_model.py
harlequelrah_fastapi/authorization/privilege_model.py
harlequelrah_fastapi/authorization/role_model.py
harlequelrah_fastapi/authorization/role_privilege_model.py
harlequelrah_fastapi/crud/__init__.py
harlequelrah_fastapi/crud/crud_forgery.py
harlequelrah_fastapi/crud/link_class.py
harlequelrah_fastapi/crud/user_crud_forgery.py
harlequelrah_fastapi/exception/__init__.py
harlequelrah_fastapi/exception/auth_exception.py
harlequelrah_fastapi/exception/custom_http_exception.py
harlequelrah_fastapi/exception/exceptions_utils.py
harlequelrah_fastapi/middleware/__init__.py
harlequelrah_fastapi/middleware/crud_middleware.py
harlequelrah_fastapi/middleware/error_middleware.py
harlequelrah_fastapi/middleware/log_middleware.py
harlequelrah_fastapi/middleware/models.py
harlequelrah_fastapi/middleware/loggerapp/__init__.py
harlequelrah_fastapi/middleware/loggerapp/log_crud.py
harlequelrah_fastapi/middleware/loggerapp/log_model.py
harlequelrah_fastapi/middleware/loggerapp/log_router.py
harlequelrah_fastapi/middleware/loggerapp/log_schema.py
harlequelrah_fastapi/router/__init__.py
harlequelrah_fastapi/router/route_config.py
harlequelrah_fastapi/router/router_crud.py
harlequelrah_fastapi/router/router_default_routes_name.py
harlequelrah_fastapi/router/router_namespace.py
harlequelrah_fastapi/router/router_provider.py
harlequelrah_fastapi/router/user_router_provider.py
harlequelrah_fastapi/security/__init__.py
harlequelrah_fastapi/security/secret.py
harlequelrah_fastapi/settings/__init__.py
harlequelrah_fastapi/settings/database.py
harlequelrah_fastapi/settings/models_metadata.py
harlequelrah_fastapi/settings/secret.py
harlequelrah_fastapi/sqlapp/__init__.py
harlequelrah_fastapi-1.0.6.dist-info/METADATA
harlequelrah_fastapi-1.0.6.dist-info/WHEEL
harlequelrah_fastapi-1.0.6.dist-info/entry_points.txt
harlequelrah_fastapi-1.0.6.dist-info/top_level.txt
harlequelrah_fastapi-1.0.6.dist-info/RECORD
