Metadata-Version: 2.1
Name: harlequelrah_fastapi
Version: 1.0.6
Summary: Package personnalisé pour faciliter  le développement avec python avec fastapi
Home-page: https://github.com/Harlequelrah/Library-harlequelrah_fastapi
Author: Harlequelrah
Author-email: maximeatsoudegbovi@example.com
Classifier: Programming Language :: Python :: 3
Classifier: License :: OSI Approved :: GNU Lesser General Public License v3 (LGPLv3)
Classifier: Operating System :: OS Independent
Requires-Python: >=3.10
Requires-Dist: fastapi[standard] >=0.112.0
Requires-Dist: alembic >=1.13.3
Requires-Dist: virtualenv >=20.26.6
Requires-Dist: mysql-connector-python >=9.0.0
